architecture/__init__.py
architecture/contracts.py
architecture/dp.py
architecture/extensions.py
architecture/log.py
architecture/py.typed
architecture/types.py
architecture/data/__init__.py
architecture/data/files.py
architecture/data/repositories.py
architecture/observability/__init__.py
architecture/observability/metrics.py
architecture/utils/__init__.py
architecture/utils/builders.py
architecture/utils/creators.py
architecture/utils/decorators.py
architecture/utils/documentation.py
architecture/utils/functions.py
architecture/utils/markers.py
architecture/utils/structs.py
architecture-0.5.50.dist-info/METADATA
architecture-0.5.50.dist-info/WHEEL
architecture-0.5.50.dist-info/RECORD
