Metadata-Version: 2.4
Name: architecture
Version: 0.5.50
Summary: Architecture is a lightweight, comprehensive framework that empowers developers to create robust, maintainable applications. By adhering to clean architecture principles and domain-driven design (DDD) patterns, weavearc provides the foundational building blocks needed for scalable, flexible, and easily testable backends. Simplify the complex and build with confidence across any architecture.
Requires-Python: >=3.13
Requires-Dist: aiocache>=0.12.3
Requires-Dist: jinja2>=3.1.5
Requires-Dist: msgspec
Requires-Dist: python-magic>=0.4.27
Requires-Dist: rich>=13.9.4
